crix/__init__.py
crix/async_client.py
crix/client.py
crix/models.py
crix-1.8.2.dist-info/LICENSE
crix-1.8.2.dist-info/METADATA
crix-1.8.2.dist-info/WHEEL
crix-1.8.2.dist-info/top_level.txt
crix-1.8.2.dist-info/RECORD
