Metadata-Version: 2.1
Name: crix
Version: 1.8.2
Summary: CRIX.IO official client
Home-page: https://github.com/blockwise/crix-client-py
Author: Baryshnikov Aleksandr (reddec)
Author-email: ab@crix.io
License: UNKNOWN
Platform: UNKNOWN
Classifier: Programming Language :: Python :: 3.6
Classifier: Operating System :: OS Independent
Classifier: License :: OSI Approved :: MIT License
Classifier: Topic :: Office/Business :: Financial
Requires-Dist: requests (~=2.21.0)
Requires-Dist: aiohttp (~=3.5.4)
